[
  {
    "year" : "2014",
    "content" : [
      {
        "month" : 12,
        "content" : [
          {
            "day" : "",
            "content" :   {
              "scale" : "ss-medium",
              "date" : "date",
              "tittle" : "《成人視界》─ 成大畢業創作攝影比賽",
              "locate" : "locate",
              "content" : "content",
              "eventHtml" : "<p class='MsoNormal' align='center' style='text-align:center'><span style='font-size:16.0pt;mso-bidi-font-size:18.0pt;font-family:&quot;微軟正黑體&quot;,sans-serif'>國立成功大學<span lang='EN-US'>104</span>級畢業生聯合會</span><span style='font-size:16.0pt;mso-bidi-font-size:18.0pt;font-family:&quot;微軟正黑體&quot;,sans-serif;mso-bidi-font-family:細明體'> </span><span style='font-size:16.0pt;mso-bidi-font-size:18.0pt;font-family:&quot;微軟正黑體&quot;,sans-serif'>《成人視界》畢業攝影比賽章程</span><span lang='EN-US' style='font-size:16.0pt;mso-bidi-font-size:18.0pt;font-family:&quot;微軟正黑體&quot;,sans-serif;mso-bidi-font-family:細明體'><o:p></o:p></span></p><p class='MsoNormal' style='margin-bottom:4.5pt;mso-layout-grid-align:none;text-autospace:none'><span lang='EN-US' style='font-size:11.5pt;font-family:&quot;Century Gothic&quot;,sans-serif;mso-fareast-font-family:微軟正黑體;mso-bidi-font-family:Wingdings;mso-font-kerning:0pt'>■ </span><span lang='EN-US' style='font-size:11.5pt;font-family:&quot;微軟正黑體&quot;,sans-serif;mso-bidi-font-family:Wingdings;mso-font-kerning:0pt'>&nbsp;</span><span style='font-size:11.5pt;font-family:&quot;微軟正黑體&quot;,sans-serif;mso-bidi-font-family:標楷體;mso-font-kerning:0pt'>主題：<a name='OLE_LINK1'><b>《 選擇 》</b></a><span lang='EN-US'><o:p></o:p></span></span></p><p class='MsoNormal' style='margin-bottom:9.0pt;mso-para-margin-bottom:.5gd'><span lang='EN-US' style='font-size:11.5pt;font-family:&quot;微軟正黑體&quot;,sans-serif;mso-bidi-font-family:Wingdings;mso-font-kerning:0pt'>■&nbsp; </span><span style='font-size:11.5pt;font-family:&quot;微軟正黑體&quot;,sans-serif;mso-bidi-font-family:標楷體;mso-font-kerning:0pt'>緣起：<span lang='EN-US'><o:p></o:p></span></span></p><p class='MsoNormal' style='margin-bottom:9.0pt;mso-para-margin-bottom:.5gd;text-indent:24.0pt'><span style='font-family:&quot;微軟正黑體&quot;,sans-serif'>往年由畢聯會舉辦的校景攝影比賽，皆深受成大愛好攝影的同學熱情參與，作品充滿畢業生對於校園的回憶與熟悉，故本屆宣傳部將在今年十二月底開始舉行全校性的校景攝影徵件宣傳，希望屆時能夠吸引更多喜愛攝影、喜愛成大的同學共襄盛舉，一起捕捉校園的美麗風景。</span><span lang='EN-US' style='font-size:11.5pt;font-family:&quot;微軟正黑體&quot;,sans-serif;mso-bidi-font-family:標楷體;mso-font-kerning:0pt'><o:p></o:p></span></p><p class='MsoNormal' style='margin-bottom:4.5pt;mso-layout-grid-align:none;text-autospace:none'><span lang='EN-US' style='font-size:11.5pt;font-family:&quot;微軟正黑體&quot;,sans-serif;mso-bidi-font-family:Wingdings;mso-font-kerning:0pt'>■&nbsp; </span><span style='font-size:11.5pt;font-family:&quot;微軟正黑體&quot;,sans-serif;mso-bidi-font-family:標楷體;mso-font-kerning:0pt'>負責人：資訊<span lang='EN-US'>104 </span>薛智豪<span lang='EN-US'><o:p></o:p></span></span></p><p class='MsoNormal'><span lang='EN-US' style='font-size:11.5pt;font-family:&quot;微軟正黑體&quot;,sans-serif;mso-bidi-font-family:Wingdings;mso-font-kerning:0pt'>■&nbsp; </span><span style='font-size:11.5pt;font-family:&quot;微軟正黑體&quot;,sans-serif;mso-bidi-font-family:標楷體;mso-font-kerning:0pt'>活動主旨：<span lang='EN-US'><o:p></o:p></span></span></p><p class='MsoNormal' style='text-indent:24.0pt;mso-layout-grid-align:none;text-autospace:none'><span style='font-family:&quot;微軟正黑體&quot;,sans-serif'>除了宣傳畢業季的到來，也希望能夠藉由攝影徵件的方式，使愛好攝影的同學在拍攝的過程中，透過鏡頭重新認識這個我們熟悉的校園，也能用不同角度將這些美麗的作品呈現在同學們眼前。除此之外，得獎作品也將收錄進畢業紀念冊中，使這個夏天珍貴的回憶永遠烙印在每個人的心中。</span><span lang='EN-US' style='font-size:11.5pt;font-family:&quot;微軟正黑體&quot;,sans-serif;mso-bidi-font-family:標楷體;mso-font-kerning:0pt'><o:p></o:p></span></p><p class='MsoNormal'><span lang='EN-US' style='font-size:11.5pt;font-family:&quot;微軟正黑體&quot;,sans-serif;mso-bidi-font-family:Wingdings;mso-font-kerning:0pt'>■&nbsp; </span><span style='font-size:11.5pt;font-family:&quot;微軟正黑體&quot;,sans-serif;mso-bidi-font-family:標楷體;mso-font-kerning:0pt'>參賽方法：<span lang='EN-US'><o:p></o:p></span></span></p><p class='MsoListParagraph' style='margin-left:18.0pt;mso-para-margin-left:0gd;text-indent:-18.0pt;mso-list:l2 level1 lfo1;mso-layout-grid-align:none;text-autospace:none'><!--[if !supportLists]--><span lang='EN-US' style='font-size:11.5pt;font-family:&quot;微軟正黑體&quot;,sans-serif;mso-bidi-font-family:微軟正黑體;mso-font-kerning:0pt'>1.<span style='font-stretch: normal; font-size: 7pt; font-family: 'Times New Roman';'>&nbsp;&nbsp;&nbsp;&nbsp;&nbsp;</span></span><!--[endif]--><span style='font-size:11.5pt;font-family:&quot;微軟正黑體&quot;,sans-serif;mso-bidi-font-family:標楷體;mso-font-kerning:0pt'>資格：國立成功大學在校生即可<span lang='EN-US'>(</span>包括大學部與碩、博班<span lang='EN-US'>)<o:p></o:p></span></span></p><p class='MsoNormal'><span lang='EN-US' style='font-size:11.5pt;font-family:&quot;微軟正黑體&quot;,sans-serif;mso-bidi-font-family:標楷體;mso-font-kerning:0pt'>2. </span><span style='font-size:11.5pt;font-family:&quot;微軟正黑體&quot;,sans-serif;mso-bidi-font-family:標楷體;mso-font-kerning:0pt'>活動時間：即日</span><span style='font-family:&quot;微軟正黑體&quot;,sans-serif'>起至 <span lang='EN-US'>104 </span>年<span lang='EN-US'> 03 </span>月<span lang='EN-US'> 01 </span>日止<span lang='EN-US'><o:p></o:p></span></span></p><p class='MsoNormal'><span lang='EN-US' style='font-size:11.5pt;font-family:&quot;微軟正黑體&quot;,sans-serif;mso-bidi-font-family:標楷體;mso-font-kerning:0pt'>3. </span><span style='font-size:11.5pt;font-family:&quot;微軟正黑體&quot;,sans-serif;mso-bidi-font-family:標楷體;mso-font-kerning:0pt'>投稿方式： <span lang='EN-US'><o:p></o:p></span></span></p><p class='MsoNormal'><span lang='EN-US' style='font-size:11.5pt;font-family:&quot;微軟正黑體&quot;,sans-serif;mso-bidi-font-family:標楷體;mso-font-kerning:0pt'>&nbsp;&nbsp;&nbsp;&nbsp;&nbsp;&nbsp;&nbsp; </span><span style='font-size:11.5pt;font-family:&quot;微軟正黑體&quot;,sans-serif;mso-bidi-font-family:標楷體;mso-font-kerning:0pt'>請以 <span lang='EN-US'>email </span>寄至 </span><span lang='EN-US' style='font-family:&quot;微軟正黑體&quot;,sans-serif'><a href='mailto:nckugraduation@gmail.com'><span style='font-size:11.5pt;mso-bidi-font-family:標楷體;color:windowtext;mso-font-kerning:0pt'>nckugraduation@gmail.com</span></a></span><span lang='EN-US' style='font-size:11.5pt;font-family:&quot;微軟正黑體&quot;,sans-serif;mso-bidi-font-family:標楷體;mso-font-kerning:0pt'> <o:p></o:p></span></p><p class='MsoNormal' style='text-indent:24.0pt;mso-layout-grid-align:none;text-autospace:none'><span style='font-size:11.5pt;font-family:&quot;微軟正黑體&quot;,sans-serif;mso-bidi-font-family:標楷體;mso-font-kerning:0pt'>標題為『系級<span lang='EN-US'>/</span>姓名<span lang='EN-US'>/</span>學號<span lang='EN-US'>/</span>參加<span lang='EN-US'> 104 </span>級畢聯會攝影比賽』<span lang='EN-US'><o:p></o:p></span></span></p><p class='MsoNormal' style='text-indent:24.0pt;mso-layout-grid-align:none;text-autospace:none'><span style='font-size:11.5pt;font-family:&quot;微軟正黑體&quot;,sans-serif;mso-bidi-font-family:標楷體;mso-font-kerning:0pt'>內含<span lang='EN-US'>:<o:p></o:p></span></span></p><p class='MsoNormal'><span lang='EN-US' style='font-size:11.5pt;font-family:&quot;微軟正黑體&quot;,sans-serif'>&nbsp;&nbsp;&nbsp;&nbsp;&nbsp;&nbsp;&nbsp; </span><span lang='EN-US' style='font-size:11.5pt;font-family:&quot;微軟正黑體&quot;,sans-serif;mso-bidi-font-family:標楷體;mso-font-kerning:0pt'>(1) </span><span style='font-size:11.5pt;font-family:&quot;微軟正黑體&quot;,sans-serif'>每件作品之<span lang='EN-US'>JPG</span>或<span lang='EN-US'>TIFF</span>電子檔案<span lang='EN-US'><o:p></o:p></span></span></p><p class='Default'><span lang='EN-US' style='font-size:11.5pt;font-family:&quot;微軟正黑體&quot;,sans-serif;color:windowtext'>&nbsp;&nbsp;&nbsp;&nbsp;&nbsp;&nbsp;&nbsp; (2) </span><span style='font-size:11.5pt;font-family:&quot;微軟正黑體&quot;,sans-serif;color:windowtext'>每件作品之電子報名表<span lang='EN-US'><o:p></o:p></span></span></p><p class='Default'><span lang='EN-US' style='font-size:11.5pt;font-family:&quot;微軟正黑體&quot;,sans-serif;color:windowtext'>&nbsp;&nbsp;&nbsp;&nbsp;&nbsp;&nbsp;&nbsp; </span><b><span style='font-size:11.5pt;font-family:&quot;微軟正黑體&quot;,sans-serif;color:windowtext'>※ 一張報名表僅能附一張照片<span lang='EN-US'> !!!!<o:p></o:p></span></span></b></p><p class='MsoNormal' style='text-indent:24.0pt;mso-layout-grid-align:none;text-autospace:none'><span style='font-size:11.5pt;font-family:&quot;微軟正黑體&quot;,sans-serif;mso-bidi-font-family:標楷體;mso-font-kerning:0pt'>請至 </span><span lang='EN-US' style='font-family:&quot;微軟正黑體&quot;,sans-serif'><a href='http://nckugraduation.tw/#download'><span style='font-size:11.5pt;mso-bidi-font-family:標楷體;color:windowtext;mso-font-kerning:0pt'>http://nckugraduation.tw/#download</span></a></span><span lang='EN-US' style='font-size:11.5pt;font-family:&quot;微軟正黑體&quot;,sans-serif;mso-bidi-font-family:標楷體;mso-font-kerning:0pt'> </span><span style='font-size:11.5pt;font-family:&quot;微軟正黑體&quot;,sans-serif;mso-bidi-font-family:標楷體;mso-font-kerning:0pt'>網站中下載報名表<span lang='EN-US'><o:p></o:p></span></span></p><p class='MsoNormal'><span lang='EN-US' style='font-size:11.5pt;font-family:&quot;微軟正黑體&quot;,sans-serif;mso-bidi-font-family:標楷體;mso-font-kerning:0pt'>4. </span><span style='font-size:11.5pt;font-family:&quot;微軟正黑體&quot;,sans-serif;mso-bidi-font-family:標楷體;mso-font-kerning:0pt'>網路人氣投票截止：<span lang='EN-US'>03 </span>月 <span lang='EN-US'>22 </span>日 <span lang='EN-US'><o:p></o:p></span></span></p><p class='MsoNormal'><span lang='EN-US' style='font-size:11.5pt;font-family:&quot;微軟正黑體&quot;,sans-serif;mso-bidi-font-family:標楷體;mso-font-kerning:0pt'>5. </span><span style='font-size:11.5pt;font-family:&quot;微軟正黑體&quot;,sans-serif;mso-bidi-font-family:標楷體;mso-font-kerning:0pt'>得獎公佈：將在 <span lang='EN-US'>03 </span>月<span lang='EN-US'> 29 </span>日另行公告 <span lang='EN-US'><o:p></o:p></span></span></p><p class='MsoNormal' style='margin-left:12.0pt;mso-para-margin-left:1.0gd;mso-layout-grid-align:none;text-autospace:none'><span lang='EN-US' style='font-size:11.5pt;font-family:&quot;微軟正黑體&quot;,sans-serif;mso-bidi-font-family:標楷體;mso-font-kerning:0pt'>A. </span><span style='font-size:11.5pt;font-family:&quot;微軟正黑體&quot;,sans-serif;mso-bidi-font-family:標楷體;mso-font-kerning:0pt'>第一組： 生活組<span lang='EN-US'><o:p></o:p></span></span></p><p class='MsoListParagraph' style='margin-left:48.0pt;mso-para-margin-left:2.5gd;text-indent:-18.0pt;mso-list:l1 level1 lfo2;mso-layout-grid-align:none;text-autospace:none'><!--[if !supportLists]--><span lang='EN-US' style='font-size:11.5pt;font-family:&quot;微軟正黑體&quot;,sans-serif;mso-bidi-font-family:微軟正黑體;mso-font-kerning:0pt'>a.<span style='font-stretch: normal; font-size: 7pt; font-family: 'Times New Roman';'>&nbsp;&nbsp;&nbsp;&nbsp;&nbsp;&nbsp;</span></span><!--[endif]--><span style='font-size:11.5pt;font-family:&quot;微軟正黑體&quot;,sans-serif;mso-bidi-font-family:標楷體;mso-font-kerning:0pt'>第一名： 獎金 <span lang='EN-US'>4000 </span>元、</span><span lang='EN-US' style='font-size:11.5pt;font-family:&quot;微軟正黑體&quot;,sans-serif;mso-bidi-font-family:Arial;mso-font-kerning:0pt'>1 </span><span style='font-size:11.5pt;font-family:&quot;微軟正黑體&quot;,sans-serif;mso-bidi-font-family:Arial;mso-font-kerning:0pt'>件紀念<span lang='EN-US'>T</span>、<span lang='EN-US'>3 </span>份傳情</span><span lang='EN-US' style='font-size:11.5pt;font-family:&quot;微軟正黑體&quot;,sans-serif;mso-bidi-font-family:標楷體;mso-font-kerning:0pt'><o:p></o:p></span></p><p class='MsoListParagraph' style='margin-left:48.0pt;mso-para-margin-left:2.5gd;text-indent:-18.0pt;mso-list:l1 level1 lfo2;mso-layout-grid-align:none;text-autospace:none'><!--[if !supportLists]--><span lang='EN-US' style='font-size:11.5pt;font-family:&quot;微軟正黑體&quot;,sans-serif;mso-bidi-font-family:微軟正黑體;mso-font-kerning:0pt'>b.<span style='font-stretch: normal; font-size: 7pt; font-family: 'Times New Roman';'>&nbsp;&nbsp;&nbsp;&nbsp;&nbsp;</span></span><!--[endif]--><span style='font-size:11.5pt;font-family:&quot;微軟正黑體&quot;,sans-serif;mso-bidi-font-family:標楷體;mso-font-kerning:0pt'>第二名： 獎金 <span lang='EN-US'>2000 </span>元、</span><span lang='EN-US' style='font-size:11.5pt;font-family:&quot;微軟正黑體&quot;,sans-serif;mso-bidi-font-family:Arial;mso-font-kerning:0pt'>1 </span><span style='font-size:11.5pt;font-family:&quot;微軟正黑體&quot;,sans-serif;mso-bidi-font-family:Arial;mso-font-kerning:0pt'>件紀念<span lang='EN-US'>T</span>、<span lang='EN-US'>2 </span>份傳情</span><span lang='EN-US' style='font-size:11.5pt;font-family:&quot;微軟正黑體&quot;,sans-serif;mso-bidi-font-family:標楷體;mso-font-kerning:0pt'><o:p></o:p></span></p><p class='MsoListParagraph' style='margin-left:48.0pt;mso-para-margin-left:2.5gd;text-indent:-18.0pt;mso-list:l1 level1 lfo2;mso-layout-grid-align:none;text-autospace:none'><!--[if !supportLists]--><span lang='EN-US' style='font-size:11.5pt;font-family:&quot;微軟正黑體&quot;,sans-serif;mso-bidi-font-family:微軟正黑體;mso-font-kerning:0pt'>c.<span style='font-stretch: normal; font-size: 7pt; font-family: 'Times New Roman';'>&nbsp;&nbsp;&nbsp;&nbsp;&nbsp;&nbsp;</span></span><!--[endif]--><span style='font-size:11.5pt;font-family:&quot;微軟正黑體&quot;,sans-serif;mso-bidi-font-family:標楷體;mso-font-kerning:0pt'>第三名： 獎金 <span lang='EN-US'>1000 </span>元、</span><span lang='EN-US' style='font-size:11.5pt;font-family:&quot;微軟正黑體&quot;,sans-serif;mso-bidi-font-family:Arial;mso-font-kerning:0pt'>1 </span><span style='font-size:11.5pt;font-family:&quot;微軟正黑體&quot;,sans-serif;mso-bidi-font-family:Arial;mso-font-kerning:0pt'>件紀念<span lang='EN-US'>T</span>、<span lang='EN-US'>1 </span>份傳情</span><span lang='EN-US' style='font-size:11.5pt;font-family:&quot;微軟正黑體&quot;,sans-serif;mso-bidi-font-family:標楷體;mso-font-kerning:0pt'><o:p></o:p></span></p><p class='MsoListParagraph' style='margin-left:48.0pt;mso-para-margin-left:2.5gd;text-indent:-18.0pt;mso-list:l1 level1 lfo2;mso-layout-grid-align:none;text-autospace:none'><!--[if !supportLists]--><span lang='EN-US' style='font-size:11.5pt;font-family:&quot;微軟正黑體&quot;,sans-serif;mso-bidi-font-family:微軟正黑體;mso-font-kerning:0pt'>d.<span style='font-stretch: normal; font-size: 7pt; font-family: 'Times New Roman';'>&nbsp;&nbsp;&nbsp;&nbsp;&nbsp;</span></span><!--[endif]--><span style='font-size:11.5pt;font-family:&quot;微軟正黑體&quot;,sans-serif;mso-bidi-font-family:標楷體;mso-font-kerning:0pt'>佳作 <span lang='EN-US'>5 </span>名：獎金<span lang='EN-US'> 500 </span>元 <span lang='EN-US'><o:p></o:p></span></span></p><p class='MsoNormal' style='margin-left:18.0pt;mso-para-margin-left:1.5gd;mso-layout-grid-align:none;text-autospace:none'><span lang='EN-US' style='font-size:11.5pt;font-family:&quot;微軟正黑體&quot;,sans-serif;mso-bidi-font-family:標楷體;mso-font-kerning:0pt'>B. </span><span style='font-size:11.5pt;font-family:&quot;微軟正黑體&quot;,sans-serif;mso-bidi-font-family:標楷體;mso-font-kerning:0pt'>第二組： 校景組<span lang='EN-US'><o:p></o:p></span></span></p><p class='MsoListParagraph' style='margin-left:48.0pt;mso-para-margin-left:0gd;text-indent:-18.0pt;mso-list:l0 level1 lfo3;mso-layout-grid-align:none;text-autospace:none'><!--[if !supportLists]--><span lang='EN-US' style='font-size:11.5pt;font-family:&quot;微軟正黑體&quot;,sans-serif;mso-bidi-font-family:微軟正黑體;mso-font-kerning:0pt'>a.<span style='font-stretch: normal; font-size: 7pt; font-family: 'Times New Roman';'>&nbsp;&nbsp;&nbsp;&nbsp;&nbsp;&nbsp;</span></span><!--[endif]--><span style='font-size:11.5pt;font-family:&quot;微軟正黑體&quot;,sans-serif;mso-bidi-font-family:標楷體;mso-font-kerning:0pt'>第一名： 獎金 <span lang='EN-US'>4000 </span>元、</span><span lang='EN-US' style='font-size:11.5pt;font-family:&quot;微軟正黑體&quot;,sans-serif;mso-bidi-font-family:Arial;mso-font-kerning:0pt'>1 </span><span style='font-size:11.5pt;font-family:&quot;微軟正黑體&quot;,sans-serif;mso-bidi-font-family:Arial;mso-font-kerning:0pt'>件紀念<span lang='EN-US'>T</span>、<span lang='EN-US'>3 </span>份傳情</span><span lang='EN-US' style='font-size:11.5pt;font-family:&quot;微軟正黑體&quot;,sans-serif;mso-bidi-font-family:標楷體;mso-font-kerning:0pt'><o:p></o:p></span></p><p class='MsoListParagraph' style='margin-left:48.0pt;mso-para-margin-left:2.5gd;text-indent:-18.0pt;mso-list:l0 level1 lfo3;mso-layout-grid-align:none;text-autospace:none'><!--[if !supportLists]--><span lang='EN-US' style='font-size:11.5pt;font-family:&quot;微軟正黑體&quot;,sans-serif;mso-bidi-font-family:微軟正黑體;mso-font-kerning:0pt'>b.<span style='font-stretch: normal; font-size: 7pt; font-family: 'Times New Roman';'>&nbsp;&nbsp;&nbsp;&nbsp;&nbsp;</span></span><!--[endif]--><span style='font-size:11.5pt;font-family:&quot;微軟正黑體&quot;,sans-serif;mso-bidi-font-family:標楷體;mso-font-kerning:0pt'>第二名： 獎金 <span lang='EN-US'>2000 </span>元、</span><span lang='EN-US' style='font-size:11.5pt;font-family:&quot;微軟正黑體&quot;,sans-serif;mso-bidi-font-family:Arial;mso-font-kerning:0pt'>1 </span><span style='font-size:11.5pt;font-family:&quot;微軟正黑體&quot;,sans-serif;mso-bidi-font-family:Arial;mso-font-kerning:0pt'>件紀念<span lang='EN-US'>T</span>、<span lang='EN-US'>2 </span>份傳情</span><span lang='EN-US' style='font-size:11.5pt;font-family:&quot;微軟正黑體&quot;,sans-serif;mso-bidi-font-family:標楷體;mso-font-kerning:0pt'><o:p></o:p></span></p><p class='MsoListParagraph' style='margin-left:48.0pt;mso-para-margin-left:2.5gd;text-indent:-18.0pt;mso-list:l0 level1 lfo3;mso-layout-grid-align:none;text-autospace:none'><!--[if !supportLists]--><span lang='EN-US' style='font-size:11.5pt;font-family:&quot;微軟正黑體&quot;,sans-serif;mso-bidi-font-family:微軟正黑體;mso-font-kerning:0pt'>c.<span style='font-stretch: normal; font-size: 7pt; font-family: 'Times New Roman';'>&nbsp;&nbsp;&nbsp;&nbsp;&nbsp;&nbsp;</span></span><!--[endif]--><span style='font-size:11.5pt;font-family:&quot;微軟正黑體&quot;,sans-serif;mso-bidi-font-family:標楷體;mso-font-kerning:0pt'>第三名： 獎金 <span lang='EN-US'>1000 </span>元、</span><span lang='EN-US' style='font-size:11.5pt;font-family:&quot;微軟正黑體&quot;,sans-serif;mso-bidi-font-family:Arial;mso-font-kerning:0pt'>1 </span><span style='font-size:11.5pt;font-family:&quot;微軟正黑體&quot;,sans-serif;mso-bidi-font-family:Arial;mso-font-kerning:0pt'>件紀念<span lang='EN-US'>T</span>、<span lang='EN-US'>1 </span>份傳情</span><span lang='EN-US' style='font-size:11.5pt;font-family:&quot;微軟正黑體&quot;,sans-serif;mso-bidi-font-family:標楷體;mso-font-kerning:0pt'><o:p></o:p></span></p><p class='MsoNormal' style='margin-left:30.0pt;mso-para-margin-left:2.5gd;mso-layout-grid-align:none;text-autospace:none'><span lang='EN-US' style='font-size:11.5pt;font-family:&quot;微軟正黑體&quot;,sans-serif;mso-bidi-font-family:標楷體;mso-font-kerning:0pt'>d. </span><span style='font-size:11.5pt;font-family:&quot;微軟正黑體&quot;,sans-serif;mso-bidi-font-family:標楷體;mso-font-kerning:0pt'>佳作<span lang='EN-US'> 5 </span>名： 獎金<span lang='EN-US'> 500 </span>元 <span lang='EN-US'><o:p></o:p></span></span></p><p class='MsoNormal' style='margin-left:18.0pt;mso-para-margin-left:1.5gd;mso-layout-grid-align:none;text-autospace:none'><span lang='EN-US' style='font-size:11.5pt;font-family:&quot;微軟正黑體&quot;,sans-serif;mso-bidi-font-family:標楷體;mso-font-kerning:0pt'><o:p>&nbsp;</o:p></span></p><p class='MsoNormal' style='margin-left:18.0pt;mso-para-margin-left:1.5gd;mso-layout-grid-align:none;text-autospace:none'><span lang='EN-US' style='font-size:11.5pt;font-family:&quot;微軟正黑體&quot;,sans-serif;mso-bidi-font-family:標楷體;mso-font-kerning:0pt'>* </span><span style='font-size:11.5pt;font-family:&quot;微軟正黑體&quot;,sans-serif;mso-bidi-font-family:標楷體;mso-font-kerning:0pt'>另有最佳分享人氣獎<span lang='EN-US'> 1 </span>名：獎金<span lang='EN-US'> 1000 </span>元<span lang='EN-US'><o:p></o:p></span></span></p><p class='MsoNormal' style='margin-left:18.0pt;mso-para-margin-left:1.5gd;mso-layout-grid-align:none;text-autospace:none'><span lang='EN-US' style='font-size:11.5pt;font-family:&quot;微軟正黑體&quot;,sans-serif;mso-bidi-font-family:標楷體;mso-font-kerning:0pt'>* FB</span><span style='font-size:11.5pt;font-family:&quot;微軟正黑體&quot;,sans-serif;mso-bidi-font-family:標楷體;mso-font-kerning:0pt'>分享獎：分享攝影比賽相簿，從分享者中抽<span lang='EN-US'>3</span>個人可獲得畢業紀念<span lang='EN-US'>T </span>乙件<span lang='EN-US'><o:p></o:p></span></span></p><p class='MsoNormal' style='margin-left:18.0pt;mso-layout-grid-align:none;text-autospace:none'><span lang='EN-US' style='font-size:11.5pt;font-family:&quot;微軟正黑體&quot;,sans-serif;mso-bidi-font-family:標楷體;mso-font-kerning:0pt'><o:p>&nbsp;</o:p></span></p><p class='MsoNormal'><span lang='EN-US' style='font-size:11.5pt;font-family:&quot;微軟正黑體&quot;,sans-serif;mso-bidi-font-family:標楷體;mso-font-kerning:0pt'>6. </span><span style='font-size:11.5pt;font-family:&quot;微軟正黑體&quot;,sans-serif;mso-bidi-font-family:標楷體;mso-font-kerning:0pt'>評選辦法： <span lang='EN-US'><o:p></o:p></span></span></p><p class='MsoNormal' style='text-indent:24.0pt;mso-layout-grid-align:none;text-autospace:none'><span style='font-size:11.5pt;font-family:&quot;微軟正黑體&quot;,sans-serif;mso-bidi-font-family:標楷體;mso-font-kerning:0pt'>初選：臉書按讚人氣投票 <span lang='EN-US'>25%</span>、三位專業攝影師評選各 <span lang='EN-US'>25%<o:p></o:p></span></span></p><p class='MsoNormal' style='margin-left:24.0pt;text-indent:24.0pt;mso-layout-grid-align:none;text-autospace:none'><span style='font-size:11.5pt;font-family:&quot;微軟正黑體&quot;,sans-serif;mso-bidi-font-family:標楷體;mso-font-kerning:0pt'>（評審作品標準：主題、創意、技巧、構圖與光影各佔 <span lang='EN-US'>20</span>％<span lang='EN-US'>)<o:p></o:p></span></span></p><p class='MsoNormal' style='text-indent:24.0pt;mso-layout-grid-align:none;text-autospace:none'><span style='font-size:11.5pt;font-family:&quot;微軟正黑體&quot;,sans-serif;mso-bidi-font-family:標楷體;mso-font-kerning:0pt'>決選：三位專業攝影師評選各佔 <span lang='EN-US'>1/3<o:p></o:p></span></span></p><p class='MsoNormal' style='margin-left:24.0pt;text-indent:24.0pt;mso-layout-grid-align:none;text-autospace:none'><span style='font-size:11.5pt;font-family:&quot;微軟正黑體&quot;,sans-serif;mso-bidi-font-family:標楷體;mso-font-kerning:0pt'>（評審作品標準：主題、想法內蘊、敘事性、美感各佔 <span lang='EN-US'>25</span>％）<span lang='EN-US'><o:p></o:p></span></span></p><p class='MsoNormal' style='margin-left:24.0pt;text-indent:24.0pt;mso-layout-grid-align:none;text-autospace:none'><span lang='EN-US' style='font-size:11.5pt;font-family:&quot;微軟正黑體&quot;,sans-serif;mso-bidi-font-family:標楷體;mso-font-kerning:0pt'><o:p>&nbsp;</o:p></span></p><p class='MsoNormal'><span lang='EN-US' style='font-size:11.5pt;font-family:&quot;微軟正黑體&quot;,sans-serif;mso-bidi-font-family:標楷體;mso-font-kerning:0pt'>7. </span><span style='font-size:11.5pt;font-family:&quot;微軟正黑體&quot;,sans-serif;mso-bidi-font-family:標楷體;mso-font-kerning:0pt'>投稿須知：<span lang='EN-US'><o:p></o:p></span></span></p><p class='MsoListParagraph' style='margin-left:36.0pt;mso-para-margin-left:0gd;text-indent:-18.0pt;mso-list:l3 level1 lfo4;mso-layout-grid-align:none;text-autospace:none'><!--[if !supportLists]--><span lang='EN-US' style='font-size: 11.5pt; font-family: 微軟正黑體, sans-serif;'>A.<span style='font-stretch: normal; font-size: 7pt; font-family: 'Times New Roman';'>&nbsp;&nbsp;&nbsp;&nbsp;&nbsp; </span></span><!--[endif]--><span style='font-size:11.5pt;font-family:&quot;微軟正黑體&quot;,sans-serif;mso-bidi-font-family:標楷體;mso-font-kerning:0pt'>需圍繞此次攝影競賽的主題《選擇》。<span lang='EN-US'><o:p></o:p></span></span></p><p class='MsoListParagraph' style='margin-left:36.0pt;mso-para-margin-left:0gd;text-indent:-18.0pt;mso-list:l3 level1 lfo4;mso-layout-grid-align:none;text-autospace:none'><!--[if !supportLists]--><span lang='EN-US' style='font-size: 11.5pt; font-family: 微軟正黑體, sans-serif;'>B.<span style='font-stretch: normal; font-size: 7pt; font-family: 'Times New Roman';'>&nbsp;&nbsp;&nbsp;&nbsp;&nbsp; </span></span><!--[endif]--><span style='font-size:11.5pt;font-family:&quot;微軟正黑體&quot;,sans-serif;mso-bidi-font-family:標楷體;mso-font-kerning:0pt'>每人每組限投<span lang='EN-US'> 3 </span>份作品（生活組限投稿 <span lang='EN-US'>3 </span>份作品，校景組限投稿 <span lang='EN-US'>3 </span>份作品），請注意參賽作品僅能透過機身或 <span lang='EN-US'>RAW&nbsp;</span>之設定，調整銳利、對比、色溫。不能再以任何軟體（<span lang='EN-US'>photoshop</span>、<span lang='EN-US'>lightroom </span>等）或其他軟體濾鏡進行改色、合成、修除、翻拍或無中生有或有中變無產生之作品，且著作不得畫線、彩繪、裁切、格放、加框、落款、加註文字。若有軟體修改、合成之爭議，將以本單位聘請專家審查意見為判定之依據。參賽者有舉證之義務，並對判定之結果不得異議。<span lang='EN-US'><o:p></o:p></span></span></p><p class='MsoListParagraph' style='margin-left:36.0pt;mso-para-margin-left:0gd;text-indent:-18.0pt;mso-list:l3 level1 lfo4;mso-layout-grid-align:none;text-autospace:none'><!--[if !supportLists]--><span lang='EN-US' style='font-size: 11.5pt; font-family: 微軟正黑體, sans-serif;'>C.<span style='font-stretch: normal; font-size: 7pt; font-family: 'Times New Roman';'>&nbsp;&nbsp;&nbsp;&nbsp;&nbsp; </span></span><!--[endif]--><span style='font-size:11.5pt;font-family:&quot;微軟正黑體&quot;,sans-serif;mso-bidi-font-family:標楷體;mso-font-kerning:0pt'>請下載報名表、作品授權同意書，並煩請每張作品附上一份（若同時投稿五份作品則需填寫五份報名表及五份同意書），以電子檔方式一同寄至</span><span lang='EN-US' style='font-family:&quot;微軟正黑體&quot;,sans-serif'><a href='mailto:nckugraduation@gmail.com'><span style='font-size:11.5pt;mso-bidi-font-family:標楷體;color:windowtext;mso-font-kerning:0pt'>nckugraduation@gmail.com</span></a></span><span lang='EN-US' style='font-size:11.5pt;font-family:&quot;微軟正黑體&quot;,sans-serif;mso-bidi-font-family:標楷體;mso-font-kerning:0pt'> </span><span style='font-size:11.5pt;font-family:&quot;微軟正黑體&quot;,sans-serif;mso-bidi-font-family:標楷體;mso-font-kerning:0pt'>。<span lang='EN-US'><o:p></o:p></span></span></p><p class='MsoNormal' style='margin-left:36.0pt;mso-layout-grid-align:none;text-autospace:none'><span style='font-size:11.5pt;font-family:&quot;微軟正黑體&quot;,sans-serif;mso-bidi-font-family:標楷體;mso-font-kerning:0pt'>電子報名表檔名請照以下規定填寫：「攝影作品參賽報名表 <u>&nbsp;作品名稱 </u>&nbsp;（生活組 <span lang='EN-US'>/ </span>校景組）」 <span lang='EN-US'><o:p></o:p></span></span></p><p class='MsoListParagraph' style='margin-left:36.0pt;mso-para-margin-left:0gd;text-indent:-18.0pt;mso-list:l3 level1 lfo4;mso-layout-grid-align:none;text-autospace:none'><!--[if !supportLists]--><span lang='EN-US' style='font-size: 11.5pt; font-family: 微軟正黑體, sans-serif;'>D.<span style='font-stretch: normal; font-size: 7pt; font-family: 'Times New Roman';'>&nbsp;&nbsp;&nbsp;&nbsp; </span></span><!--[endif]--><span style='font-size:11.5pt;font-family:&quot;微軟正黑體&quot;,sans-serif;mso-bidi-font-family:標楷體;mso-font-kerning:0pt'>若稿件不足或作品素質欠佳將導致名次從缺。 <span lang='EN-US'><o:p></o:p></span></span></p><p class='MsoListParagraph' style='margin-left:36.0pt;mso-para-margin-left:0gd;text-indent:-18.0pt;mso-list:l3 level1 lfo4;mso-layout-grid-align:none;text-autospace:none'><!--[if !supportLists]--><span lang='EN-US' style='font-size: 11.5pt; font-family: 微軟正黑體, sans-serif;'>E.<span style='font-stretch: normal; font-size: 7pt; font-family: 'Times New Roman';'>&nbsp;&nbsp;&nbsp;&nbsp;&nbsp;&nbsp; </span></span><!--[endif]--><span style='font-size:11.5pt;font-family:&quot;微軟正黑體&quot;,sans-serif;mso-bidi-font-family:標楷體;mso-font-kerning:0pt'>參賽作品限未曾公開發表者，畫素品質須在六百萬畫素以上、長邊不得小於 <span lang='EN-US'>300dpi </span>以上規格之 <span lang='EN-US'>JPG</span>（<span lang='EN-US'>fine, highquality</span>）或 <span lang='EN-US'>TIFF </span>檔，繳交電子檔即可。 <span lang='EN-US'><o:p></o:p></span></span></p><p class='MsoListParagraph' style='margin-left:36.0pt;mso-para-margin-left:0gd;text-indent:-18.0pt;mso-list:l3 level1 lfo4;mso-layout-grid-align:none;text-autospace:none'><!--[if !supportLists]--><span lang='EN-US' style='font-size: 11.5pt; font-family: 微軟正黑體, sans-serif;'>F.<span style='font-stretch: normal; font-size: 7pt; font-family: 'Times New Roman';'>&nbsp;&nbsp;&nbsp;&nbsp;&nbsp;&nbsp; </span></span><!--[endif]--><span style='font-size:11.5pt;font-family:&quot;微軟正黑體&quot;,sans-serif;mso-bidi-font-family:標楷體;mso-font-kerning:0pt'>網路投票若有發現投稿者以不正當之行為增加選票，則予取消資格！<span lang='EN-US'><o:p></o:p></span></span></p><p class='Default' style='margin-left:36.0pt;text-indent:-18.0pt;mso-list:l3 level1 lfo4'><!--[if !supportLists]--><span lang='EN-US' style='font-size: 11.5pt; font-family: 微軟正黑體, sans-serif;'>G.<span style='font-stretch: normal; font-size: 7pt; font-family: 'Times New Roman';'>&nbsp;&nbsp;&nbsp;&nbsp; </span></span><!--[endif]--><span style='font-size:11.5pt;font-family:&quot;微軟正黑體&quot;,sans-serif;color:windowtext'>比賽本誠信原則，得獎作品如有偽冒身分、抄襲、拷貝或經檢舉曾參加任何公開攝影比賽得獎或展出，或曾於各傳媒網路刊登者，一經查證屬實，一律取消資格，獎項將不予遞補。已領取獎項者，主辦單位將追回原頒獎項之獎金及獎座（證書）。其違反著作權法令等由參賽者自行負責，概與主辦單位無關，但凡涉及詐欺等民事、刑事時，主辦單位有權追究。<span lang='EN-US'><o:p></o:p></span></span></p><p class='MsoListParagraph' style='margin-left:36.0pt;mso-para-margin-left:0gd;text-indent:-18.0pt;mso-list:l3 level1 lfo4;mso-layout-grid-align:none;text-autospace:none'><!--[if !supportLists]--><span lang='EN-US' style='font-size: 11.5pt; font-family: 微軟正黑體, sans-serif;'>H.<span style='font-stretch: normal; font-size: 7pt; font-family: 'Times New Roman';'>&nbsp;&nbsp;&nbsp;&nbsp; </span></span><!--[endif]--><span style='font-size:11.5pt;font-family:&quot;微軟正黑體&quot;,sans-serif;mso-bidi-font-family:標楷體;mso-font-kerning:0pt'>投稿作品及文案之版權為<span lang='EN-US'>104</span>級國立成功大學畢業生聯合會所有，並享有更動活動細節之權利。<span lang='EN-US'><o:p></o:p></span></span></p><p class='MsoListParagraph' style='margin-left:36.0pt;mso-para-margin-left:0gd;text-indent:-18.0pt;mso-list:l3 level1 lfo4;mso-layout-grid-align:none;text-autospace:none'><!--[if !supportLists]--><span lang='EN-US' style='font-size: 11.5pt; font-family: 微軟正黑體, sans-serif;'>I.<span style='font-stretch: normal; font-size: 7pt; font-family: 'Times New Roman';'>&nbsp;&nbsp;&nbsp;&nbsp;&nbsp;&nbsp;&nbsp;&nbsp;</span></span><!--[endif]--><span style='font-size:11.5pt;font-family:&quot;微軟正黑體&quot;,sans-serif;mso-bidi-font-family:標楷體;mso-font-kerning:0pt'>如有未盡事宜，主辦單位得隨時補充解釋之。<span lang='EN-US'><o:p></o:p></span></span></p><p class='MsoListParagraph' style='margin-left:36.0pt;mso-para-margin-left:0gd;text-indent:-18.0pt;mso-list:l3 level1 lfo4;mso-layout-grid-align:none;text-autospace:none'><!--[if !supportLists]--><span lang='EN-US' style='font-size: 11.5pt; font-family: 微軟正黑體, sans-serif;'>J.<span style='font-stretch: normal; font-size: 7pt; font-family: 'Times New Roman';'>&nbsp;&nbsp;&nbsp;&nbsp;&nbsp;&nbsp;&nbsp;</span></span><!--[endif]--><span style='font-size:11.5pt;font-family:&quot;微軟正黑體&quot;,sans-serif;mso-bidi-font-family:標楷體;mso-font-kerning:0pt'>凡參加本攝影比賽者，視同承認本簡章之各項規定。<span lang='EN-US'><o:p></o:p></span></span></p><p class='MsoListParagraph' style='margin-left:36.0pt;mso-para-margin-left:0gd;text-indent:-18.0pt;mso-list:l3 level1 lfo4;mso-layout-grid-align:none;text-autospace:none'><!--[if !supportLists]--><span lang='EN-US' style='font-size: 11.5pt; font-family: 微軟正黑體, sans-serif;'>K.<span style='font-stretch: normal; font-size: 7pt; font-family: 'Times New Roman';'>&nbsp;&nbsp;&nbsp;&nbsp;&nbsp; </span></span><!--[endif]--><span style='font-size:11.5pt;font-family:&quot;微軟正黑體&quot;,sans-serif;mso-bidi-font-family:標楷體;mso-font-kerning:0pt'>參賽者（及其法定代理人）應保證參賽著作確由參賽者獨立創作，並享有完整之著作權，並未曾在其他比賽得獎、著作不得違反公共秩序或善良風俗。該作品之著作權若有爭議或已授權或讓與他人者請勿參賽，如涉著作權侵害之法律責任由參賽者自行負責，與主辦單位無關。<span lang='EN-US'><o:p></o:p></span></span></p><p class='MsoNormal' style='margin-left:12.0pt;mso-layout-grid-align:none;text-autospace:none'><span lang='EN-US' style='font-size:11.5pt;font-family:&quot;微軟正黑體&quot;,sans-serif;mso-bidi-font-family:標楷體;mso-font-kerning:0pt'><o:p>&nbsp;</o:p></span></p><p class='MsoNormal'><span lang='EN-US' style='font-size:11.5pt;font-family:&quot;微軟正黑體&quot;,sans-serif;mso-bidi-font-family:標楷體;mso-font-kerning:0pt'>8. </span><span style='font-size:11.5pt;font-family:&quot;微軟正黑體&quot;,sans-serif;mso-bidi-font-family:標楷體;mso-font-kerning:0pt'>公開展覽：預計<span lang='EN-US'>104</span>年<span lang='EN-US'>4</span>月舉行，詳情陸續公告於畢聯會網站 </span><span lang='EN-US' style='font-family:&quot;微軟正黑體&quot;,sans-serif'><a href='http://nckugraduation.tw/'><span style='font-size:11.5pt;mso-bidi-font-family:標楷體;color:windowtext;mso-font-kerning:0pt'>http://nckugraduation.tw</span></a></span><span style='font-size:11.5pt;font-family:&quot;微軟正黑體&quot;,sans-serif;mso-bidi-font-family:標楷體;mso-font-kerning:0pt'>。</span><span lang='EN-US' style='font-size:9.0pt;font-family:&quot;微軟正黑體&quot;,sans-serif;mso-bidi-font-family:Arial;background:white'><o:p></o:p></span></p><p class='MsoNormal'><span lang='EN-US' style='font-size:11.5pt;font-family:&quot;微軟正黑體&quot;,sans-serif;mso-bidi-font-family:標楷體;mso-font-kerning:0pt'><o:p>&nbsp;</o:p></span></p><p class='MsoNormal' style='text-align:justify;text-justify:inter-ideograph'><span lang='EN-US' style='font-size:11.5pt;font-family:&quot;微軟正黑體&quot;,sans-serif;mso-bidi-font-family:標楷體;mso-font-kerning:0pt'>9. </span><span style='font-size:11.5pt;font-family:&quot;微軟正黑體&quot;,sans-serif;mso-bidi-font-family:標楷體;mso-font-kerning:0pt'>聯絡方式：資訊<span lang='EN-US'>104 </span>薛智豪<span lang='EN-US'> za7788az@live.com 0956879886</span></span><span lang='EN-US' style='font-family:&quot;微軟正黑體&quot;,sans-serif'><o:p></o:p></span></p>"
            }
          },
          {
            "day" : "",
            "content" :   {
              "scale" : "ss-medium",
              "date" : "date",
              "tittle" : "成大 104 級畢業歌曲徵選",
              "locate" : "locate",
              "content" : "content"
            }
          }
        ]
      }
    ]
  },
  {
    "year" : "2015",
    "content" : [
      {
        "month" : 3,
        "content" : [
          {
            "day" : "",
            "content" :   {
              "scale" : "ss-medium",
              "date" : "date",
              "tittle" : "名人講座",
              "locate" : "locate",
              "content" : "content"
            }
          }
        ]
      },
      {
        "month" : 4,
        "content" : [
          {
            "day" : "",
            "content" :   {
              "scale" : "ss-medium",
              "date" : "date",
              "tittle" : "畢業傳情",
              "locate" : "locate",
              "content" : "content"
            }
          },
          {
            "day" : "",
            "content" :   {
              "scale" : "ss-medium",
              "date" : "date",
              "tittle" : "已畢業學長姐心得分享會",
              "locate" : "locate",
              "content" : "content"
            }
          }
        ]
      },
      {
        "month" : 5,
        "content" : [
          {
            "day" : "",
            "content" :   {
              "scale" : "ss-medium",
              "date" : "date",
              "tittle" : "畢業紀念冊出爐",
              "locate" : "locate",
              "content" : "content"
            }
          }
        ]
      },
      {
        "month" : 6,
        "content" : [
          {
            "day" : "",
            "content" :   {
              "scale" : "ss-medium",
              "date" : "date",
              "tittle" : "畢業演唱會",
              "locate" : "locate",
              "content" : "content"
            }
          },
          {
            "day" : "",
            "content" :   {
              "scale" : "ss-medium",
              "date" : "date",
              "tittle" : "餞別宴",
              "locate" : "locate",
              "content" : "content"
            }
          }
        ]
      }
    ]
  }
]
